CHANGES.txt
bootstrap.py
buildout.cfg
setup.py
bootstrap/bootstrap.py
src/lovely/__init__.py
src/lovely.responsecache.egg-info/PKG-INFO
src/lovely.responsecache.egg-info/SOURCES.txt
src/lovely.responsecache.egg-info/dependency_links.txt
src/lovely.responsecache.egg-info/namespace_packages.txt
src/lovely.responsecache.egg-info/not-zip-safe
src/lovely.responsecache.egg-info/requires.txt
src/lovely.responsecache.egg-info/top_level.txt
src/lovely/responsecache/BROWSER.txt
src/lovely/responsecache/LICENSE.txt
src/lovely/responsecache/PURGE.txt
src/lovely/responsecache/PURGEDISK.txt
src/lovely/responsecache/PURGEVIEW.txt
src/lovely/responsecache/README.txt
src/lovely/responsecache/__init__.py
src/lovely/responsecache/configure.zcml
src/lovely/responsecache/credentials.py
src/lovely/responsecache/credentials.txt
src/lovely/responsecache/event.py
src/lovely/responsecache/ftesting.zcml
src/lovely/responsecache/interfaces.py
src/lovely/responsecache/lovely.responsecache-configure.zcml
src/lovely/responsecache/lovely.responsecache-meta.zcml
src/lovely/responsecache/meta.zcml
src/lovely/responsecache/namespace.py
src/lovely/responsecache/purge.py
src/lovely/responsecache/tests.py
src/lovely/responsecache/view.py
src/lovely/responsecache/zcml.py
src/lovely/responsecache/zcml.txt
src/lovely/responsecache/testing/__init__.py
src/lovely/responsecache/testing/configure.zcml
src/lovely/responsecache/testing/purge.py
src/lovely/responsecache/testing/purge.txt
src/lovely/responsecache/testing/test.pt
src/lovely/responsecache/testing/viewlet.pt
src/lovely/responsecache/testing/views.py