Metadata-Version: 1.0
Name: lovely.responsecache
Version: 1.3.0
Summary: Cache results of ContentProviders
Home-page: http://svn.zope.org/lovely.responsecache
Author: Lovely Systems
Author-email: office@lovelysystems.com
License: ZPL 2.1
Keywords: responsecache zope zope3
Platform: UNKNOWN
